<?xml version="1.0" encoding="utf-8"?>
<!DOCTYPE documentInfo>
<documentInfo url="/home/lucas/Documents/Computer_Science/Algorithms/Courses/ZCY01/Notes/基础/算法基础入门班第一课.pdf">
 <generalInfo>
  <history>
   <oldPage viewport="0;C2:0.499737:0.465888:1"/>
   <oldPage viewport="1"/>
   <oldPage viewport="2"/>
   <oldPage viewport="3"/>
   <oldPage viewport="4"/>
   <current viewport="5"/>
  </history>
  <views>
   <view name="PageView">
    <zoom value="1.24827" mode="2"/>
    <continuous mode="1"/>
    <viewMode mode="0"/>
    <trimMargins value="0"/>
   </view>
  </views>
 </generalInfo>
</documentInfo>
